pytest_subtests/__init__.py
pytest_subtests/plugin.py
pytest_subtests/py.typed
pytest_subtests-0.14.0.dist-info/LICENSE
pytest_subtests-0.14.0.dist-info/METADATA
pytest_subtests-0.14.0.dist-info/WHEEL
pytest_subtests-0.14.0.dist-info/entry_points.txt
pytest_subtests-0.14.0.dist-info/top_level.txt
pytest_subtests-0.14.0.dist-info/RECORD
